noyaki/__init__.py
noyaki/noyaki.py
noyaki-0.2.0.dist-info/LICENSE
noyaki-0.2.0.dist-info/METADATA
noyaki-0.2.0.dist-info/WHEEL
noyaki-0.2.0.dist-info/top_level.txt
noyaki-0.2.0.dist-info/RECORD
