Metadata-Version: 2.1
Name: noyaki
Version: 0.2.0
Summary: character span label to tokenized base label for Japanese text
Home-page: https://github.com/ken11/noyaki
Author: ken
Author-email: kent.adachi@adachi-honten.net
License: UNKNOWN
Platform: UNKNOWN
Classifier: Programming Language :: Python :: 3
Classifier: License :: OSI Approved :: MIT License
Classifier: Operating System :: OS Independent
Requires-Python: >=3.6
